scor/__init__.py
scor/data.py
scor/losses.py
scor/metrics.py
scor/models.py
scor/training.py
scor-0.2.2.dist-info/LICENSE.txt
scor-0.2.2.dist-info/METADATA
scor-0.2.2.dist-info/WHEEL
scor-0.2.2.dist-info/RECORD
